{"0": {"start_time": 1, "end_time": 1, "exe_time": 35, "total_needSend": 190, "total_needReceive": 0, "input_links": [], "out_links": [[[1, 190, [], [], 0, 27, 35]]], "visited": 0, "mapto": 27}, "1": {"start_time": 1, "end_time": 1, "exe_time": 20, "total_needSend": 1250, "total_needReceive": 190, "input_links": [["0", 190]], "out_links": [[[10, 200, [], [], 0, 35, 28]], [[3, 170, [], [], 0, 35, 19]], [[4, 140, [], [], 0, 35, 26]], [[5, 130, [], [], 0, 35, 43]], [[6, 170, [], [], 0, 35, 36]], [[7, 160, [], [], 0, 35, 34]], [[8, 100, [], [], 0, 35, 29]], [[9, 180, [], [], 0, 35, 20]]], "visited": 0, "mapto": 35}, "2": {"start_time": 1, "end_time": 1, "exe_time": 57, "total_needSend": 210, "total_needReceive": 1340, "input_links": [["3", 170], ["4", 170], ["5", 140], ["6", 190], ["7", 150], ["8", 200], ["9", 140], ["10", 180]], "out_links": [[[11, 210, [], [], 0, 11, 18]]], "visited": 0, "mapto": 11}, "3": {"start_time": 1, "end_time": 1, "exe_time": 64, "total_needSend": 170, "total_needReceive": 170, "input_links": [["1", 170]], "out_links": [[[2, 170, [], [], 0, 19, 11]]], "visited": 0, "mapto": 19}, "4": {"start_time": 1, "end_time": 1, "exe_time": 48, "total_needSend": 170, "total_needReceive": 140, "input_links": [["1", 140]], "out_links": [[[2, 170, [], [], 0, 26, 11]]], "visited": 0, "mapto": 26}, "5": {"start_time": 1, "end_time": 1, "exe_time": 56, "total_needSend": 140, "total_needReceive": 130, "input_links": [["1", 130]], "out_links": [[[2, 140, [], [], 0, 43, 11]]], "visited": 0, "mapto": 43}, "6": {"start_time": 1, "end_time": 1, "exe_time": 55, "total_needSend": 190, "total_needReceive": 170, "input_links": [["1", 170]], "out_links": [[[2, 190, [], [], 0, 36, 11]]], "visited": 0, "mapto": 36}, "7": {"start_time": 1, "end_time": 1, "exe_time": 54, "total_needSend": 150, "total_needReceive": 160, "input_links": [["1", 160]], "out_links": [[[2, 150, [], [], 0, 34, 11]]], "visited": 0, "mapto": 34}, "8": {"start_time": 1, "end_time": 1, "exe_time": 52, "total_needSend": 200, "total_needReceive": 100, "input_links": [["1", 100]], "out_links": [[[2, 200, [], [], 0, 29, 11]]], "visited": 0, "mapto": 29}, "9": {"start_time": 1, "end_time": 1, "exe_time": 51, "total_needSend": 140, "total_needReceive": 180, "input_links": [["1", 180]], "out_links": [[[2, 140, [], [], 0, 20, 11]]], "visited": 0, "mapto": 20}, "10": {"start_time": 1, "end_time": 1, "exe_time": 50, "total_needSend": 180, "total_needReceive": 200, "input_links": [["1", 200]], "out_links": [[[2, 180, [], [], 0, 28, 11]]], "visited": 0, "mapto": 28}, "11": {"start_time": 1, "end_time": 1, "exe_time": 48, "total_needSend": 0, "total_needReceive": 210, "input_links": [["2", 210]], "out_links": [], "visited": 0, "mapto": 18}}